{
  "db_name": "PostgreSQL",
  "query": "\n            SELECT a.id, a.email, a.name, a.disabled_at, a.created_at\n            FROM account a\n            JOIN github_identity gi ON a.id = gi.account_id\n            WHERE gi.github_user_id = $1\n            ",
  "describe": {
    "columns": [
      {
        "ordinal": 0,
        "name": "id",
        "type_info": "Int8"
      },
      {
        "ordinal": 1,
        "name": "email",
        "type_info": "Text"
      },
      {
        "ordinal": 2,
        "name": "name",
        "type_info": "Text"
      },
      {
        "ordinal": 3,
        "name": "disabled_at",
        "type_info": "Timestamptz"
      },
      {
        "ordinal": 4,
        "name": "created_at",
        "type_info": "Timestamptz"
      }
    ],
    "parameters": {
      "Left": [
        "Int8"
      ]
    },
    "nullable": [
      false,
      false,
      true,
      true,
      false
    ]
  },
  "hash": "952ad997562c47e2fcd61224edf62d94d6d5391cb418fb6c28cf7ddac922c623"
}
